leveldb/__init__.py
leveldb/_leveldb.cpython-312-darwin.so
leveldb/_leveldb.pyi
leveldb/_version.py
leveldb/py.typed
amulet_leveldb-1.0.2.dist-info/LICENSE
amulet_leveldb-1.0.2.dist-info/METADATA
amulet_leveldb-1.0.2.dist-info/WHEEL
amulet_leveldb-1.0.2.dist-info/top_level.txt
amulet_leveldb-1.0.2.dist-info/RECORD
