Metadata-Version: 2.1
Name: amulet-leveldb
Version: 1.0.2
Summary: A Cython wrapper for Mojang's custom LevelDB.
Home-page: https://www.amuletmc.com
Author: James Clare
Author-email: amuleteditor@gmail.com
Platform: any
Classifier: Programming Language :: Python :: 3
Classifier: Operating System :: OS Independent
Requires-Python: ~=3.8
License-File: LICENSE
Provides-Extra: docs
Requires-Dist: Sphinx>=1.7.4; extra == "docs"
Requires-Dist: sphinx-autodoc-typehints>=1.3.0; extra == "docs"
Requires-Dist: sphinx_rtd_theme>=0.3.1; extra == "docs"
Provides-Extra: dev
Requires-Dist: black>=22.3; extra == "dev"
Requires-Dist: pre_commit>=1.11.1; extra == "dev"
Requires-Dist: cython~=3.0; extra == "dev"
Requires-Dist: mypy; extra == "dev"
